klctool/__init__.py
klctool/adjustimage.py
klctool/common.py
klctool/convert2odt.py
klctool/hiragana.py
klctool/main.py
config/klctool/config.toml
config/klctool/gemini-2.0-flash-exp.api_key.toml
config/klctool/gemini-2.0-flash-exp.prompt.toml
config/klctool/klctool-edit.lua
config/klctool/klctool.odt
config/klctool/paper-size.toml
klctool-0.1.6.dist-info/METADATA
klctool-0.1.6.dist-info/WHEEL
klctool-0.1.6.dist-info/entry_points.txt
klctool-0.1.6.dist-info/licenses/LICENSE
klctool-0.1.6.dist-info/RECORD
