Metadata-Version: 2.4
Name: klctool
Version: 0.1.6
Summary: Karaoke Lyrics Card Creation Support Tool
Project-URL: Homepage, https://github.com/AmasaShiro/klctool
Project-URL: Issues, https://github.com/AmasaShiro/klctool/issues
Author: AmasaShiro
License-Expression: Apache-2.0
License-File: LICENSE
Keywords: karaoke,klctool,lyrics,utilities
Classifier: Natural Language :: Japanese
Classifier: Topic :: Utilities
Requires-Python: >=3.13
Requires-Dist: google-generativeai>=0.8.4
Requires-Dist: pillow>=11.1.0
Requires-Dist: toml>=0.10.2
